MANIFEST.in
README.markdown
changelog.markdown
setup.py
bin/luiti
luiti/__init__.py
luiti.egg-info/PKG-INFO
luiti.egg-info/SOURCES.txt
luiti.egg-info/dependency_links.txt
luiti.egg-info/not-zip-safe
luiti.egg-info/pbr.json
luiti.egg-info/requires.txt
luiti.egg-info/top_level.txt
luiti/daemon/__init__.py
luiti/daemon/graph.py
luiti/daemon/ptm.py
luiti/daemon/query_engine/__init__.py
luiti/daemon/query_engine/builder.py
luiti/daemon/query_engine/create_task.py
luiti/daemon/query_engine/params.py
luiti/daemon/utils/__init__.py
luiti/daemon/utils/cache.py
luiti/daemon/utils/string.py
luiti/daemon/utils/task_storage.py
luiti/daemon/utils/template.py
luiti/daemon/web/__init__.py
luiti/daemon/web/assets.py
luiti/daemon/web/code_render.py
luiti/daemon/web/handlers.py
luiti/daemon/web/server.py
luiti/java/MultipleTextFiles.java
luiti/luigi_decorators/__init__.py
luiti/luigi_decorators/as_a_luiti_task.py
luiti/luigi_decorators/check_date_range.py
luiti/luigi_decorators/check_runtime_range.py
luiti/luigi_decorators/mr_local.py
luiti/luigi_decorators/multiple_text_files.py
luiti/luigi_decorators/persist_files.py
luiti/luigi_decorators/plug_packages.py
luiti/luigi_decorators/ref_tasks.py
luiti/luigi_extensions/__init__.py
luiti/luigi_extensions/create_python_package.py
luiti/luigi_extensions/hadoop_ext.py
luiti/luigi_extensions/luigi_root_context.py
luiti/luigi_extensions/manage_decorators.py
luiti/luigi_extensions/parameter.py
luiti/luigi_extensions/root_task.py
luiti/luigi_extensions/task_base.py
luiti/luigi_extensions/task_init.py
luiti/manager/__init__.py
luiti/manager/active_packages.py
luiti/manager/cli.py
luiti/manager/config.py
luiti/manager/dep.py
luiti/manager/files.py
luiti/manager/generate_from_templates.py
luiti/manager/lazy_data.py
luiti/manager/loader.py
luiti/manager/package_map.py
luiti/manager/sys_argv.py
luiti/manager/table.py
luiti/schedule/__init__.py
luiti/schedule/sensor_schedule.py
luiti/task_templates/__init__.py
luiti/task_templates/other/__init__.py
luiti/task_templates/other/hive_task.py
luiti/task_templates/other/mongo_import_task.py
luiti/task_templates/other/static_file.py
luiti/task_templates/time/__init__.py
