Metadata-Version: 1.1
Name: luiti
Version: 0.2.2
Summary: Luiti = Luigi + time
Home-page: http://github.com/luiti/luiti/
Author: David Chen
Author-email: mvjome@gmail.com
License: MIT
Platform: any
Classifier: Intended Audience :: Developers
Classifier: Operating System :: OS Independent
Classifier: Programming Language :: Python
Classifier: Topic :: Software Development :: Libraries :: Python Modules
